sthali_core/__init__.py
sthali_core/__main__.py
sthali_core/scripts/__init__.py
sthali_core/scripts/commons.py
sthali_core/scripts/templates/docstring.md
sthali_core/scripts/templates/index.md
sthali_core/scripts/templates/installation.md
sthali_core/scripts/templates/license.md
sthali_core/scripts/templates/logo.svg
sthali_core/scripts/templates/mkdocs.yml
sthali_core/scripts/templates/requirements.md
sthali_core/scripts/templates/usage.md
sthali_core/utils/__init__.py
sthali_core/utils/base.py
sthali_core/utils/enum_clients.py
sthali_core/utils/run_server.py
sthali_core-0.0.11.dist-info/licenses/LICENSE
sthali_core-0.0.11.dist-info/METADATA
sthali_core-0.0.11.dist-info/WHEEL
sthali_core-0.0.11.dist-info/entry_points.txt
sthali_core-0.0.11.dist-info/top_level.txt
sthali_core-0.0.11.dist-info/RECORD
